fgrequests.py
fgrequests-0.1.1.dist-info/LICENSE
fgrequests-0.1.1.dist-info/METADATA
fgrequests-0.1.1.dist-info/WHEEL
fgrequests-0.1.1.dist-info/top_level.txt
fgrequests-0.1.1.dist-info/RECORD
