Metadata-Version: 2.1
Name: fgrequests
Version: 0.1.1
Summary: Fastest async group request package for Python
Home-page: https://github.com/faridlu/fgrequests
Author: Farid Chowdhury
Author-email: faridstudylu@gmail.com
License: UNKNOWN
Keywords: Fastest async group requests python multiple threading
Platform: UNKNOWN
Classifier: Environment :: Web Environment
Classifier: Intended Audience :: Developers
Classifier: License :: OSI Approved :: BSD License
Classifier: Operating System :: OS Independent
Classifier: Programming Language :: Python
Classifier: Programming Language :: Python :: 2.7
Classifier: Programming Language :: Python :: 3
Classifier: Programming Language :: Python :: 3.6
Classifier: Programming Language :: Python :: 3.7
Classifier: Topic :: Software Development :: Libraries :: Python Modules
Requires-Dist: requests
Requires-Dist: futures ; python_version == "2.7"
